it4u_web_crawler/__init__.py
it4u_web_crawler/web_crawler.py
it4u_web_crawler-1.0.14.dist-info/METADATA
it4u_web_crawler-1.0.14.dist-info/WHEEL
it4u_web_crawler-1.0.14.dist-info/top_level.txt
it4u_web_crawler-1.0.14.dist-info/RECORD
